cmixf/__init__.py
cmixf/_version.py
cmixf/parser.py
cmixf/tests/__init__.py
cmixf/tests/test_cmixf.py
cmixf-0.2.0.dist-info/METADATA
cmixf-0.2.0.dist-info/WHEEL
cmixf-0.2.0.dist-info/entry_points.txt
cmixf-0.2.0.dist-info/top_level.txt
cmixf-0.2.0.dist-info/RECORD
